{"name":"felixoi.com Status Page","short_name":"felixoi.com Status Page","description":"Status page for all services provided by felixoi.com","icons":[{"src":"/static/icons/icon_16.eea143.png","sizes":"16x16","type":"image/png"},{"src":"/static/icons/icon_120.eea143.png","sizes":"120x120","type":"image/png"},{"src":"/static/icons/icon_144.eea143.png","sizes":"144x144","type":"image/png"},{"src":"/static/icons/icon_152.eea143.png","sizes":"152x152","type":"image/png"},{"src":"/static/icons/icon_192.eea143.png","sizes":"192x192","type":"image/png"},{"src":"/static/icons/icon_384.eea143.png","sizes":"384x384","type":"image/png"},{"src":"/static/icons/icon_512.eea143.png","sizes":"512x512","type":"image/png"}],"start_url":"/?standalone=true&utm_source=web_app&utm_medium=pwa","display":"standalone","background_color":"#ffffff","theme_color":"#1b1f23","lang":"en","version":"0.5.0"}